{
    "products": [
        {
            "id": "1",
            "name": "T-Shirt-1",
            "category": "T-Shirts",
            "productCode": "1010",
            "description": "T-Shirt",
            "price": "400",
            "in_stock": 1,
            "status": "Available",
            "background": "red",
            "image": "/pdt1.png",
            "sizes": [
                {
                    "id": "1",
                    "sizeTitle": "S",
                    "in_stock": 1,
                    "status": "Available",
                    "price": "300",
                    "colors": [
                        {
                            "id": 1,
                            "color": "#06b6d4",
                            "status": "Available"
                        },
                        {
                            "id": 2,
                            "color": "#10b981",
                            "status": "Available"
                        },
                        {
                            "id": 3,
                            "color": "#3b82f6",
                            "status": "Available"
                        }
                    ]
                },
                {
                    "id": "2",
                    "sizeTitle": "M",
                    "in_stock": 0,
                    "status": "Not Available",
                    "price": "400",
                    "colors": [
                        {
                            "id": 1,
                            "color": "#06b6d4",
                            "status": "Available"
                        },
                        {
                            "id": 2,
                            "color": "#10b981",
                            "status": "Available"
                        },
                        {
                            "id": 3,
                            "color": "#3b82f6",
                            "status": "Available"
                        }
                    ]
                },
                {
                    "id": "3",
                    "sizeTitle": "L",
                    "in_stock": 1,
                    "status": "Available",
                    "price": "500",
                    "colors": [
                        {
                            "id": 1,
                            "color": "#06b6d4",
                            "status": "Available"
                        },
                        {
                            "id": 2,
                            "color": "#10b981",
                            "status": "Available"
                        },
                        {
                            "id": 3,
                            "color": "#3b82f6",
                            "status": "Available"
                        }
                    ]
                }
            ],
            "images": [
                {
                    "id": 1,
                    "link": "https://i.ibb.co/ctqDbv2/pngegg-5.png"
                },
                {
                    "id": 2,
                    "link": "https://i.ibb.co/pvgg4n3/pngegg-4.png"
                },
                {
                    "id": 3,
                    "link": "https://i.ibb.co/c35P2B5/pngegg-3.png"
                },
                {
                    "id": 4,
                    "link": "https://i.ibb.co/h8jsRX6/pngegg-2.png"
                }
            ]
        },
        {
            "id": "2",
            "name": "T-Shirt-2",
            "category": "T-Shirts",
            "productCode": "1011",
            "description": "T-Shirt",
            "price": "450",
            "in_stock": 0,
            "status": "Not Available",
            "background": "black",
            "image": "/pdt2.png",
            "sizes": [
                {
                    "id": "1",
                    "sizeTitle": "S",
                    "in_stock": 1,
                    "status": "Available",
                    "price": "300",
                    "colors": [
                        {
                            "id": 1,
                            "color": "#06b6d4",
                            "status": "Available"
                        },
                        {
                            "id": 2,
                            "color": "#10b981",
                            "status": "Available"
                        },
                        {
                            "id": 3,
                            "color": "#3b82f6",
                            "status": "Available"
                        }
                    ]
                },
                {
                    "id": "2",
                    "sizeTitle": "M",
                    "in_stock": 0,
                    "status": "Not Available",
                    "price": "400",
                    "colors": [
                        {
                            "id": 1,
                            "color": "#06b6d4",
                            "status": "Available"
                        },
                        {
                            "id": 2,
                            "color": "#10b981",
                            "status": "Available"
                        },
                        {
                            "id": 3,
                            "color": "#3b82f6",
                            "status": "Available"
                        }
                    ]
                },
                {
                    "id": "3",
                    "sizeTitle": "L",
                    "in_stock": 1,
                    "status": "Available",
                    "price": "500",
                    "colors": [
                        {
                            "id": 1,
                            "color": "#06b6d4",
                            "status": "Available"
                        },
                        {
                            "id": 2,
                            "color": "#10b981",
                            "status": "Available"
                        },
                        {
                            "id": 3,
                            "color": "#3b82f6",
                            "status": "Available"
                        }
                    ]
                }
            ],
            "images": [
                {
                    "id": 1,
                    "link": "https://i.ibb.co/ctqDbv2/pngegg-5.png"
                },
                {
                    "id": 2,
                    "link": "https://i.ibb.co/pvgg4n3/pngegg-4.png"
                },
                {
                    "id": 3,
                    "link": "https://i.ibb.co/c35P2B5/pngegg-3.png"
                },
                {
                    "id": 4,
                    "link": "https://i.ibb.co/h8jsRX6/pngegg-2.png"
                }
            ]
        },
        {
            "id": "3",
            "name": "T-Shirt-3",
            "category": "T-Shirts",
            "productCode": "1012",
            "description": "T-Shirt",
            "price": "350",
            "in_stock": 1,
            "status": "Available",
            "background": "red",
            "image": "/pdt3.png",
            "sizes": [
                {
                    "id": "1",
                    "sizeTitle": "S",
                    "in_stock": 1,
                    "status": "Available",
                    "price": "300",
                    "colors": [
                        {
                            "id": 1,
                            "color": "#06b6d4",
                            "status": "Available"
                        },
                        {
                            "id": 2,
                            "color": "#10b981",
                            "status": "Available"
                        },
                        {
                            "id": 3,
                            "color": "#3b82f6",
                            "status": "Available"
                        }
                    ]
                },
                {
                    "id": "2",
                    "sizeTitle": "M",
                    "in_stock": 0,
                    "status": "Not Available",
                    "price": "400",
                    "colors": [
                        {
                            "id": 1,
                            "color": "#06b6d4",
                            "status": "Available"
                        },
                        {
                            "id": 2,
                            "color": "#10b981",
                            "status": "Available"
                        },
                        {
                            "id": 3,
                            "color": "#3b82f6",
                            "status": "Available"
                        }
                    ]
                },
                {
                    "id": "3",
                    "sizeTitle": "L",
                    "in_stock": 1,
                    "status": "Available",
                    "price": "500",
                    "colors": [
                        {
                            "id": 1,
                            "color": "#06b6d4",
                            "status": "Available"
                        },
                        {
                            "id": 2,
                            "color": "#10b981",
                            "status": "Available"
                        },
                        {
                            "id": 3,
                            "color": "#3b82f6",
                            "status": "Available"
                        }
                    ]
                }
            ],
            "images": [
                {
                    "id": 1,
                    "link": "https://i.ibb.co/ctqDbv2/pngegg-5.png"
                },
                {
                    "id": 2,
                    "link": "https://i.ibb.co/pvgg4n3/pngegg-4.png"
                },
                {
                    "id": 3,
                    "link": "https://i.ibb.co/c35P2B5/pngegg-3.png"
                },
                {
                    "id": 4,
                    "link": "https://i.ibb.co/h8jsRX6/pngegg-2.png"
                }
            ]
        },
        {
            "id": "4",
            "name": "T-Shirt-1",
            "category": "T-Shirts",
            "productCode": "1010",
            "description": "T-Shirt",
            "price": "400",
            "in_stock": 1,
            "status": "Available",
            "background": "red",
            "image": "/pdt1.png",
            "sizes": [
                {
                    "id": "1",
                    "sizeTitle": "S",
                    "in_stock": 1,
                    "status": "Available",
                    "price": "300",
                    "colors": [
                        {
                            "id": 1,
                            "color": "#06b6d4",
                            "status": "Available"
                        },
                        {
                            "id": 2,
                            "color": "#10b981",
                            "status": "Available"
                        },
                        {
                            "id": 3,
                            "color": "#3b82f6",
                            "status": "Available"
                        }
                    ]
                },
                {
                    "id": "2",
                    "sizeTitle": "M",
                    "in_stock": 0,
                    "status": "Not Available",
                    "price": "400",
                    "colors": [
                        {
                            "id": 1,
                            "color": "#06b6d4",
                            "status": "Available"
                        },
                        {
                            "id": 2,
                            "color": "#10b981",
                            "status": "Available"
                        },
                        {
                            "id": 3,
                            "color": "#3b82f6",
                            "status": "Available"
                        }
                    ]
                },
                {
                    "id": "3",
                    "sizeTitle": "L",
                    "in_stock": 1,
                    "status": "Available",
                    "price": "500",
                    "colors": [
                        {
                            "id": 1,
                            "color": "#06b6d4",
                            "status": "Available"
                        },
                        {
                            "id": 2,
                            "color": "#10b981",
                            "status": "Available"
                        },
                        {
                            "id": 3,
                            "color": "#3b82f6",
                            "status": "Available"
                        }
                    ]
                }
            ],
            "images": [
                {
                    "id": 1,
                    "link": "https://i.ibb.co/ctqDbv2/pngegg-5.png"
                },
                {
                    "id": 2,
                    "link": "https://i.ibb.co/pvgg4n3/pngegg-4.png"
                },
                {
                    "id": 3,
                    "link": "https://i.ibb.co/c35P2B5/pngegg-3.png"
                },
                {
                    "id": 4,
                    "link": "https://i.ibb.co/h8jsRX6/pngegg-2.png"
                }
            ]
        },
        {
            "id": "5",
            "name": "T-Shirt-2",
            "category": "T-Shirts",
            "productCode": "1011",
            "description": "T-Shirt",
            "price": "450",
            "in_stock": 0,
            "status": "Not Available",
            "background": "black",
            "image": "/pdt2.png",
            "sizes": [
                {
                    "id": "1",
                    "sizeTitle": "S",
                    "in_stock": 1,
                    "status": "Available",
                    "price": "300",
                    "colors": [
                        {
                            "id": 1,
                            "color": "#06b6d4",
                            "status": "Available"
                        },
                        {
                            "id": 2,
                            "color": "#10b981",
                            "status": "Available"
                        },
                        {
                            "id": 3,
                            "color": "#3b82f6",
                            "status": "Available"
                        }
                    ]
                },
                {
                    "id": "2",
                    "sizeTitle": "M",
                    "in_stock": 0,
                    "status": "Not Available",
                    "price": "400",
                    "colors": [
                        {
                            "id": 1,
                            "color": "#06b6d4",
                            "status": "Available"
                        },
                        {
                            "id": 2,
                            "color": "#10b981",
                            "status": "Available"
                        },
                        {
                            "id": 3,
                            "color": "#3b82f6",
                            "status": "Available"
                        }
                    ]
                },
                {
                    "id": "3",
                    "sizeTitle": "L",
                    "in_stock": 1,
                    "status": "Available",
                    "price": "500",
                    "colors": [
                        {
                            "id": 1,
                            "color": "#06b6d4",
                            "status": "Available"
                        },
                        {
                            "id": 2,
                            "color": "#10b981",
                            "status": "Available"
                        },
                        {
                            "id": 3,
                            "color": "#3b82f6",
                            "status": "Available"
                        }
                    ]
                }
            ],
            "images": [
                {
                    "id": 1,
                    "link": "https://i.ibb.co/ctqDbv2/pngegg-5.png"
                },
                {
                    "id": 2,
                    "link": "https://i.ibb.co/pvgg4n3/pngegg-4.png"
                },
                {
                    "id": 3,
                    "link": "https://i.ibb.co/c35P2B5/pngegg-3.png"
                },
                {
                    "id": 4,
                    "link": "https://i.ibb.co/h8jsRX6/pngegg-2.png"
                }
            ]
        },
        {
            "id": "6",
            "name": "T-Shirt-3",
            "category": "T-Shirts",
            "productCode": "1012",
            "description": "T-Shirt",
            "price": "350",
            "in_stock": 1,
            "status": "Available",
            "background": "red",
            "image": "/pdt3.png",
            "sizes": [
                {
                    "id": "1",
                    "sizeTitle": "S",
                    "in_stock": 1,
                    "status": "Available",
                    "price": "300",
                    "colors": [
                        {
                            "id": 1,
                            "color": "#06b6d4",
                            "status": "Available"
                        },
                        {
                            "id": 2,
                            "color": "#10b981",
                            "status": "Available"
                        },
                        {
                            "id": 3,
                            "color": "#3b82f6",
                            "status": "Available"
                        }
                    ]
                },
                {
                    "id": "2",
                    "sizeTitle": "M",
                    "in_stock": 0,
                    "status": "Not Available",
                    "price": "400",
                    "colors": [
                        {
                            "id": 1,
                            "color": "#06b6d4",
                            "status": "Available"
                        },
                        {
                            "id": 2,
                            "color": "#10b981",
                            "status": "Available"
                        },
                        {
                            "id": 3,
                            "color": "#3b82f6",
                            "status": "Available"
                        }
                    ]
                },
                {
                    "id": "3",
                    "sizeTitle": "L",
                    "in_stock": 1,
                    "status": "Available",
                    "price": "500",
                    "colors": [
                        {
                            "id": 1,
                            "color": "#06b6d4",
                            "status": "Available"
                        },
                        {
                            "id": 2,
                            "color": "#10b981",
                            "status": "Available"
                        },
                        {
                            "id": 3,
                            "color": "#3b82f6",
                            "status": "Available"
                        }
                    ]
                }
            ],
            "images": [
                {
                    "id": 1,
                    "link": "https://i.ibb.co/ctqDbv2/pngegg-5.png"
                },
                {
                    "id": 2,
                    "link": "https://i.ibb.co/pvgg4n3/pngegg-4.png"
                },
                {
                    "id": 3,
                    "link": "https://i.ibb.co/c35P2B5/pngegg-3.png"
                },
                {
                    "id": 4,
                    "link": "https://i.ibb.co/h8jsRX6/pngegg-2.png"
                }
            ]
        },
        {
            "id": "7",
            "name": "T-Shirt-1",
            "category": "T-Shirts",
            "productCode": "1010",
            "description": "T-Shirt",
            "price": "400",
            "in_stock": 1,
            "status": "Available",
            "background": "red",
            "image": "/pdt1.png",
            "sizes": [
                {
                    "id": "1",
                    "sizeTitle": "S",
                    "in_stock": 1,
                    "status": "Available",
                    "price": "300",
                    "colors": [
                        {
                            "id": 1,
                            "color": "#06b6d4",
                            "status": "Available"
                        },
                        {
                            "id": 2,
                            "color": "#10b981",
                            "status": "Available"
                        },
                        {
                            "id": 3,
                            "color": "#3b82f6",
                            "status": "Available"
                        }
                    ]
                },
                {
                    "id": "2",
                    "sizeTitle": "M",
                    "in_stock": 0,
                    "status": "Not Available",
                    "price": "400",
                    "colors": [
                        {
                            "id": 1,
                            "color": "#06b6d4",
                            "status": "Available"
                        },
                        {
                            "id": 2,
                            "color": "#10b981",
                            "status": "Available"
                        },
                        {
                            "id": 3,
                            "color": "#3b82f6",
                            "status": "Available"
                        }
                    ]
                },
                {
                    "id": "3",
                    "sizeTitle": "L",
                    "in_stock": 1,
                    "status": "Available",
                    "price": "500",
                    "colors": [
                        {
                            "id": 1,
                            "color": "#06b6d4",
                            "status": "Available"
                        },
                        {
                            "id": 2,
                            "color": "#10b981",
                            "status": "Available"
                        },
                        {
                            "id": 3,
                            "color": "#3b82f6",
                            "status": "Available"
                        }
                    ]
                }
            ],
            "images": [
                {
                    "id": 1,
                    "link": "https://i.ibb.co/ctqDbv2/pngegg-5.png"
                },
                {
                    "id": 2,
                    "link": "https://i.ibb.co/pvgg4n3/pngegg-4.png"
                },
                {
                    "id": 3,
                    "link": "https://i.ibb.co/c35P2B5/pngegg-3.png"
                },
                {
                    "id": 4,
                    "link": "https://i.ibb.co/h8jsRX6/pngegg-2.png"
                }
            ]
        },
        {
            "id": "8",
            "name": "T-Shirt-2",
            "category": "T-Shirts",
            "productCode": "1011",
            "description": "T-Shirt",
            "price": "450",
            "in_stock": 0,
            "status": "Not Available",
            "background": "black",
            "image": "/pdt2.png",
            "sizes": [
                {
                    "id": "1",
                    "sizeTitle": "S",
                    "in_stock": 1,
                    "status": "Available",
                    "price": "300",
                    "colors": [
                        {
                            "id": 1,
                            "color": "#06b6d4",
                            "status": "Available"
                        },
                        {
                            "id": 2,
                            "color": "#10b981",
                            "status": "Available"
                        },
                        {
                            "id": 3,
                            "color": "#3b82f6",
                            "status": "Available"
                        }
                    ]
                },
                {
                    "id": "2",
                    "sizeTitle": "M",
                    "in_stock": 0,
                    "status": "Not Available",
                    "price": "400",
                    "colors": [
                        {
                            "id": 1,
                            "color": "#06b6d4",
                            "status": "Available"
                        },
                        {
                            "id": 2,
                            "color": "#10b981",
                            "status": "Available"
                        },
                        {
                            "id": 3,
                            "color": "#3b82f6",
                            "status": "Available"
                        }
                    ]
                },
                {
                    "id": "3",
                    "sizeTitle": "L",
                    "in_stock": 1,
                    "status": "Available",
                    "price": "500",
                    "colors": [
                        {
                            "id": 1,
                            "color": "#06b6d4",
                            "status": "Available"
                        },
                        {
                            "id": 2,
                            "color": "#10b981",
                            "status": "Available"
                        },
                        {
                            "id": 3,
                            "color": "#3b82f6",
                            "status": "Available"
                        }
                    ]
                }
            ],
            "images": [
                {
                    "id": 1,
                    "link": "https://i.ibb.co/ctqDbv2/pngegg-5.png"
                },
                {
                    "id": 2,
                    "link": "https://i.ibb.co/pvgg4n3/pngegg-4.png"
                },
                {
                    "id": 3,
                    "link": "https://i.ibb.co/c35P2B5/pngegg-3.png"
                },
                {
                    "id": 4,
                    "link": "https://i.ibb.co/h8jsRX6/pngegg-2.png"
                }
            ]
        },
        {
            "id": "9",
            "name": "T-Shirt-3",
            "category": "T-Shirts",
            "productCode": "1012",
            "description": "T-Shirt",
            "price": "350",
            "in_stock": 1,
            "status": "Available",
            "background": "red",
            "image": "/pdt3.png",
            "sizes": [
                {
                    "id": "1",
                    "sizeTitle": "S",
                    "in_stock": 1,
                    "status": "Available",
                    "price": "300",
                    "colors": [
                        {
                            "id": 1,
                            "color": "#06b6d4",
                            "status": "Available"
                        },
                        {
                            "id": 2,
                            "color": "#10b981",
                            "status": "Available"
                        },
                        {
                            "id": 3,
                            "color": "#3b82f6",
                            "status": "Available"
                        }
                    ]
                },
                {
                    "id": "2",
                    "sizeTitle": "M",
                    "in_stock": 0,
                    "status": "Not Available",
                    "price": "400",
                    "colors": [
                        {
                            "id": 1,
                            "color": "#06b6d4",
                            "status": "Available"
                        },
                        {
                            "id": 2,
                            "color": "#10b981",
                            "status": "Available"
                        },
                        {
                            "id": 3,
                            "color": "#3b82f6",
                            "status": "Available"
                        }
                    ]
                },
                {
                    "id": "3",
                    "sizeTitle": "L",
                    "in_stock": 1,
                    "status": "Available",
                    "price": "500",
                    "colors": [
                        {
                            "id": 1,
                            "color": "#06b6d4",
                            "status": "Available"
                        },
                        {
                            "id": 2,
                            "color": "#10b981",
                            "status": "Available"
                        },
                        {
                            "id": 3,
                            "color": "#3b82f6",
                            "status": "Available"
                        }
                    ]
                }
            ],
            "images": [
                {
                    "id": 1,
                    "link": "https://i.ibb.co/ctqDbv2/pngegg-5.png"
                },
                {
                    "id": 2,
                    "link": "https://i.ibb.co/pvgg4n3/pngegg-4.png"
                },
                {
                    "id": 3,
                    "link": "https://i.ibb.co/c35P2B5/pngegg-3.png"
                },
                {
                    "id": 4,
                    "link": "https://i.ibb.co/h8jsRX6/pngegg-2.png"
                }
            ]
        },
        {
            "id": "10",
            "name": "T-Shirt-1",
            "category": "T-Shirts",
            "productCode": "1010",
            "description": "T-Shirt",
            "price": "400",
            "in_stock": 1,
            "status": "Available",
            "background": "red",
            "image": "/pdt1.png",
            "sizes": [
                {
                    "id": "1",
                    "sizeTitle": "S",
                    "in_stock": 1,
                    "status": "Available",
                    "price": "300",
                    "colors": [
                        {
                            "id": 1,
                            "color": "#06b6d4",
                            "status": "Available"
                        },
                        {
                            "id": 2,
                            "color": "#10b981",
                            "status": "Available"
                        },
                        {
                            "id": 3,
                            "color": "#3b82f6",
                            "status": "Available"
                        }
                    ]
                },
                {
                    "id": "2",
                    "sizeTitle": "M",
                    "in_stock": 0,
                    "status": "Not Available",
                    "price": "400",
                    "colors": [
                        {
                            "id": 1,
                            "color": "#06b6d4",
                            "status": "Available"
                        },
                        {
                            "id": 2,
                            "color": "#10b981",
                            "status": "Available"
                        },
                        {
                            "id": 3,
                            "color": "#3b82f6",
                            "status": "Available"
                        }
                    ]
                },
                {
                    "id": "3",
                    "sizeTitle": "L",
                    "in_stock": 1,
                    "status": "Available",
                    "price": "500",
                    "colors": [
                        {
                            "id": 1,
                            "color": "#06b6d4",
                            "status": "Available"
                        },
                        {
                            "id": 2,
                            "color": "#10b981",
                            "status": "Available"
                        },
                        {
                            "id": 3,
                            "color": "#3b82f6",
                            "status": "Available"
                        }
                    ]
                }
            ],
            "images": [
                {
                    "id": 1,
                    "link": "https://i.ibb.co/ctqDbv2/pngegg-5.png"
                },
                {
                    "id": 2,
                    "link": "https://i.ibb.co/pvgg4n3/pngegg-4.png"
                },
                {
                    "id": 3,
                    "link": "https://i.ibb.co/c35P2B5/pngegg-3.png"
                },
                {
                    "id": 4,
                    "link": "https://i.ibb.co/h8jsRX6/pngegg-2.png"
                }
            ]
        },
        {
            "id": "11",
            "name": "T-Shirt-2",
            "category": "T-Shirts",
            "productCode": "1011",
            "description": "T-Shirt",
            "price": "450",
            "in_stock": 0,
            "status": "Not Available",
            "background": "black",
            "image": "/pdt2.png",
            "sizes": [
                {
                    "id": "1",
                    "sizeTitle": "S",
                    "in_stock": 1,
                    "status": "Available",
                    "price": "300",
                    "colors": [
                        {
                            "id": 1,
                            "color": "#06b6d4",
                            "status": "Available"
                        },
                        {
                            "id": 2,
                            "color": "#10b981",
                            "status": "Available"
                        },
                        {
                            "id": 3,
                            "color": "#3b82f6",
                            "status": "Available"
                        }
                    ]
                },
                {
                    "id": "2",
                    "sizeTitle": "M",
                    "in_stock": 0,
                    "status": "Not Available",
                    "price": "400",
                    "colors": [
                        {
                            "id": 1,
                            "color": "#06b6d4",
                            "status": "Available"
                        },
                        {
                            "id": 2,
                            "color": "#10b981",
                            "status": "Available"
                        },
                        {
                            "id": 3,
                            "color": "#3b82f6",
                            "status": "Available"
                        }
                    ]
                },
                {
                    "id": "3",
                    "sizeTitle": "L",
                    "in_stock": 1,
                    "status": "Available",
                    "price": "500",
                    "colors": [
                        {
                            "id": 1,
                            "color": "#06b6d4",
                            "status": "Available"
                        },
                        {
                            "id": 2,
                            "color": "#10b981",
                            "status": "Available"
                        },
                        {
                            "id": 3,
                            "color": "#3b82f6",
                            "status": "Available"
                        }
                    ]
                }
            ],
            "images": [
                {
                    "id": 1,
                    "link": "https://i.ibb.co/ctqDbv2/pngegg-5.png"
                },
                {
                    "id": 2,
                    "link": "https://i.ibb.co/pvgg4n3/pngegg-4.png"
                },
                {
                    "id": 3,
                    "link": "https://i.ibb.co/c35P2B5/pngegg-3.png"
                },
                {
                    "id": 4,
                    "link": "https://i.ibb.co/h8jsRX6/pngegg-2.png"
                }
            ]
        },
        {
            "id": "12",
            "name": "T-Shirt-3",
            "category": "T-Shirts",
            "productCode": "1012",
            "description": "T-Shirt",
            "price": "350",
            "in_stock": 1,
            "status": "Available",
            "background": "red",
            "image": "/pdt3.png",
            "sizes": [
                {
                    "id": "1",
                    "sizeTitle": "S",
                    "in_stock": 1,
                    "status": "Available",
                    "price": "300",
                    "colors": [
                        {
                            "id": 1,
                            "color": "#06b6d4",
                            "status": "Available"
                        },
                        {
                            "id": 2,
                            "color": "#10b981",
                            "status": "Available"
                        },
                        {
                            "id": 3,
                            "color": "#3b82f6",
                            "status": "Available"
                        }
                    ]
                },
                {
                    "id": "2",
                    "sizeTitle": "M",
                    "in_stock": 0,
                    "status": "Not Available",
                    "price": "400",
                    "colors": [
                        {
                            "id": 1,
                            "color": "#06b6d4",
                            "status": "Available"
                        },
                        {
                            "id": 2,
                            "color": "#10b981",
                            "status": "Available"
                        },
                        {
                            "id": 3,
                            "color": "#3b82f6",
                            "status": "Available"
                        }
                    ]
                },
                {
                    "id": "3",
                    "sizeTitle": "L",
                    "in_stock": 1,
                    "status": "Available",
                    "price": "500",
                    "colors": [
                        {
                            "id": 1,
                            "color": "#06b6d4",
                            "status": "Available"
                        },
                        {
                            "id": 2,
                            "color": "#10b981",
                            "status": "Available"
                        },
                        {
                            "id": 3,
                            "color": "#3b82f6",
                            "status": "Available"
                        }
                    ]
                }
            ],
            "images": [
                {
                    "id": 1,
                    "link": "https://i.ibb.co/ctqDbv2/pngegg-5.png"
                },
                {
                    "id": 2,
                    "link": "https://i.ibb.co/pvgg4n3/pngegg-4.png"
                },
                {
                    "id": 3,
                    "link": "https://i.ibb.co/c35P2B5/pngegg-3.png"
                },
                {
                    "id": 4,
                    "link": "https://i.ibb.co/h8jsRX6/pngegg-2.png"
                }
            ]
        }
    ],
    "colors": [
        {
            "id": 1,
            "color": "#a855f7",
            "backColor": "#e9d5ff"
        },
        {
            "id": 2,
            "color": "#f97316",
            "backColor": "#fed7aa"
        },
        {
            "id": 3,
            "color": "#eab308",
            "backColor": "#fef08a"
        },
        {
            "id": 4,
            "color": "#10b981",
            "backColor": "#a7f3d0"
        },
        {
            "id": 5,
            "color": "#14b8a6",
            "backColor": "#99f6e4"
        },
        {
            "id": 6,
            "color": "#06b6d4",
            "backColor": "#a5f3fc"
        },
        {
            "id": 7,
            "color": "#3b82f6",
            "backColor": "#bfdbfe"
        },
        {
            "id": 8,
            "color": "#a855f7",
            "backColor": "#e9d5ff"
        },
        {
            "id": 9,
            "color": "#8b5cf6",
            "backColor": "#ddd6fe"
        },
        {
            "id": 10,
            "color": "#f97316",
            "backColor": "#fed7aa"
        },
        {
            "id": 11,
            "color": "#eab308",
            "backColor": "#fef08a"
        },
        {
            "id": 12,
            "color": "#10b981",
            "backColor": "#a7f3d0"
        }
    ],
    "dashboard": [
        {
            "id": "1",
            "orderNo": "1000",
            "customerName": "Name 1",
            "orderDate": "02/02/2023",
            "expectedDate": "05/02/2023",
            "deliveryDate": "03/02/2023",
            "status": "Delivered",
            "statusCode": 1,
            "payment": "COD",
            "paymentCode": 1,
            "address": "Baldipukur Bazar, Baldipukur, Mithapukur, Rangpur",
            "phone": "017X-XXXXXXX",
            "invoiceNo": "1000",
            "total": "2000",
            "payMethod": "COD",
            "payPhone": "",
            "transactionID": "",
            "trackID": "1245",
            "subTotal": "2000",
            "tax": "0.00",
            "products": [
                {
                    "id": 1,
                    "image": "https://i.ibb.co/nsMn8s2/pdt.png",
                    "name": "Product 1",
                    "price": "200",
                    "quantity": "1",
                    "total": "200"
                },
                {
                    "id": 2,
                    "image": "/pdt.png",
                    "name": "Product 2",
                    "price": "200",
                    "quantity": "3",
                    "total": "200"
                },
                {
                    "id": 3,
                    "image": "/pdt.png",
                    "name": "Product 3",
                    "price": "200",
                    "quantity": "2",
                    "total": "200"
                }
            ]
        },
        {
            "id": "2",
            "orderNo": "1001",
            "customerName": "Name 2",
            "orderDate": "02/02/2023",
            "expectedDate": "05/02/2023",
            "deliveryDate": "03/02/2023",
            "status": "Processing","statusCode": 2,
            "payment": "Paid",
            
            "paymentCode": 2,
            "address": "Baldipukur Bazar, Baldipukur, Mithapukur, Rangpur",
            "phone": "017X-XXXXXXX",
            "invoiceNo": "1001",
            "total": "2000",
            "payMethod": "Bkash",
            "payPhone": "017X-XXXXXXXX",
            "transactionID": "ABC123",
            "trackID": "1245",
            "subTotal": "2000",
            "tax": "0.00",
            "products": [
                {
                    "id": 1,
                    "image": "https://i.ibb.co/nsMn8s2/pdt.png",
                    "name": "Product 1",
                    "price": "200",
                    "quantity": "1",
                    "total": "200"
                }
            ]
        },
        {
            "id": "3",
            "orderNo": "1002",
            "customerName": "Name 3",
            "orderDate": "03/03/2023",
            "expectedDate": "05/03/2023",
            "deliveryDate": "03/03/2023",
            "status": "On The Way",
            "statusCode": 3,
            "payment": "Paid",
            "paymentCode": 2,
            "address": "Baldipukur Bazar, Baldipukur, Mithapukur, Rangpur",
            "phone": "017X-XXXXXXX",
            "invoiceNo": "1002",
            "total": "3000",
            "payMethod": "Bkash",
            "payPhone": "017X-XXXXXXXX",
            "transactionID": "DEF456",
            "trackID": "1246",
            "subTotal": "3000",
            "tax": "0.00",
            "products": [
                {
                    "id": 1,
                    "image": "https://i.ibb.co/nsMn8s2/pdt.png",
                    "name": "Product 1",
                    "price": "200",
                    "quantity": "1",
                    "total": "200"
                },
                {
                    "id": 2,
                    "image": "/pdt.png",
                    "name": "Product 2",
                    "price": "200",
                    "quantity": "3",
                    "total": "200"
                }
            ]
        }
    ],
    "products-1000": [
        {
            "id": 1,
            "image": "https://i.ibb.co/nsMn8s2/pdt.png",
            "name": "Product 1",
            "price": "200",
            "quantity": "1",
            "total": "200"
        },
        {
            "id": 2,
            "image": "/pdt.png",
            "name": "Product 2",
            "price": "200",
            "quantity": "3",
            "total": "200"
        },
        {
            "id": 3,
            "image": "/pdt.png",
            "name": "Product 3",
            "price": "200",
            "quantity": "2",
            "total": "200"
        }
    ],
    "products-1001": [
        {
            "id": 1,
            "image": "https://i.ibb.co/nsMn8s2/pdt.png",
            "name": "Product 1",
            "price": "200",
            "quantity": "1",
            "total": "200"
        }
    ],
    "products-1002": [
        {
            "id": 1,
            "image": "https://i.ibb.co/nsMn8s2/pdt.png",
            "name": "Product 1",
            "price": "200",
            "quantity": "1",
            "total": "200"
        },
        {
            "id": 2,
            "image": "/pdt.png",
            "name": "Product 2",
            "price": "200",
            "quantity": "3",
            "total": "200"
        }
    ]
}